bg_utils/__init__.py
bg_utils/_version.py
bg_utils/event_publisher.py
bg_utils/local_plugin.py
bg_utils/pika.py
bg_utils/plugin_logging_loader.py
bg_utils/mongo/__init__.py
bg_utils/mongo/fields.py
bg_utils/mongo/models.py
bg_utils/mongo/parser.py
bg_utils/mongo/util.py
bg_utils/thrift/beergarden.thrift
bg_utils-2.4.11.dist-info/AUTHORS.rst
bg_utils-2.4.11.dist-info/LICENSE.md
bg_utils-2.4.11.dist-info/METADATA
bg_utils-2.4.11.dist-info/WHEEL
bg_utils-2.4.11.dist-info/top_level.txt
bg_utils-2.4.11.dist-info/RECORD
