Metadata-Version: 2.1
Name: bg-utils
Version: 2.4.11
Summary: Shared utilities for beer-garden application components
Home-page: https://beer-garden.io/
Author: The beer-garden Team
Author-email: 
License: MIT
Platform: UNKNOWN
Requires-Dist: brewtils (<3)
Requires-Dist: mongoengine (<0.16)
Requires-Dist: passlib (<1.8)
Requires-Dist: pytz (<2019)
Requires-Dist: ruamel.yaml (<0.16)
Requires-Dist: thriftpy2 (<0.5)
Requires-Dist: yapconf (>=0.3.3)
